odoo/addons/contract_payment_mode_brand/README.rst
odoo/addons/contract_payment_mode_brand/__init__.py
odoo/addons/contract_payment_mode_brand/__manifest__.py
odoo/addons/contract_payment_mode_brand/i18n/contract_payment_mode_brand.pot
odoo/addons/contract_payment_mode_brand/readme/CONTRIBUTORS.rst
odoo/addons/contract_payment_mode_brand/readme/DESCRIPTION.rst
odoo/addons/contract_payment_mode_brand/readme/USAGE.rst
odoo/addons/contract_payment_mode_brand/static/description/icon.png
odoo/addons/contract_payment_mode_brand/static/description/index.html
odoo/addons/contract_payment_mode_brand/views/contract_contract.xml
odoo12_addon_contract_payment_mode_brand-12.0.1.0.0.99.dev3.dist-info/METADATA
odoo12_addon_contract_payment_mode_brand-12.0.1.0.0.99.dev3.dist-info/WHEEL
odoo12_addon_contract_payment_mode_brand-12.0.1.0.0.99.dev3.dist-info/top_level.txt
odoo12_addon_contract_payment_mode_brand-12.0.1.0.0.99.dev3.dist-info/RECORD
